xplan_tools/interface/__init__.py
xplan_tools/interface/base.py
xplan_tools/interface/db.py
xplan_tools/interface/gml.py
xplan_tools/interface/jsonfg.py
xplan_tools/interface/shape.py
xplan_tools/main.py
xplan_tools/model/__init__.py
xplan_tools/model/adapters/__init__.py
xplan_tools/model/adapters/coretable.py
xplan_tools/model/adapters/gml.py
xplan_tools/model/adapters/jsonfg.py
xplan_tools/model/appschema/__init__.py
xplan_tools/model/appschema/definitions.py
xplan_tools/model/appschema/inspire_base.py
xplan_tools/model/appschema/inspire_base2.py
xplan_tools/model/appschema/inspire_plu40.py
xplan_tools/model/appschema/xplan41.py
xplan_tools/model/appschema/xplan54.py
xplan_tools/model/appschema/xplan60.py
xplan_tools/model/appschema/xplan61.py
xplan_tools/model/appschema/xtrasse20.py
xplan_tools/model/appschema/xwp09.py
xplan_tools/model/base.py
xplan_tools/model/migrations/env.py
xplan_tools/model/migrations/script.py.mako
xplan_tools/model/migrations/versions/3c3445a58565_base_schema.py
xplan_tools/model/migrations/versions/f8b74c08ec07_add_refs_indexes_ensure_polygon_ccw.py
xplan_tools/model/orm.py
xplan_tools/resources/styles.py
xplan_tools/settings/__init__.py
xplan_tools/settings/settings.py
xplan_tools/transform/__init__.py
xplan_tools/transform/mappingtables/XPlanToINSPIRE-SupplementaryRegulation_2_6_2025-10-08.xlsx
xplan_tools/transform/mappingtables/XPlanToINSPIRE-ZoningElement_2_6_2025-10-08.xlsx
xplan_tools/transform/mappingtables/XPlanToINSPIREFeatures_2_6_2025-10-08.xlsx
xplan_tools/transform/migrate_41_54.py
xplan_tools/transform/migrate_54_60.py
xplan_tools/transform/migrate_60_61.py
xplan_tools/transform/migrate_6x_plu.py
xplan_tools/transform/transformer.py
xplan_tools/util/__init__.py
xplan_tools/util/style.py
xplan_tools/util/validate.py
xplan_tools-1.13.1.dist-info/METADATA
xplan_tools-1.13.1.dist-info/WHEEL
xplan_tools-1.13.1.dist-info/entry_points.txt
xplan_tools-1.13.1.dist-info/licenses/LICENSE.md
xplan_tools-1.13.1.dist-info/RECORD
