Metadata-Version: 2.4
Name: xplan-tools
Version: 1.13.1
Summary: Manage XPlanung data
License: EUPL-1.2-or-later
License-File: LICENSE.md
Author: Tobias Kraft
Author-email: tobias.kraft@gv.hamburg.de
Requires-Python: >=3.10,<3.14
Classifier: Development Status :: 5 - Production/Stable
Classifier: Framework :: Pydantic :: 2
Classifier: License :: OSI Approved :: European Union Public Licence 1.2 (EUPL 1.2)
Classifier: Operating System :: OS Independent
Classifier: Programming Language :: Python :: 3
Requires-Dist: alembic (>=1.16.4,<2)
Requires-Dist: deprecated
Requires-Dist: gdal (>=3.6.3)
Requires-Dist: geoalchemy2 (>=0.16)
Requires-Dist: httpx (>=0.27.2)
Requires-Dist: lxml (>=5.3.0)
Requires-Dist: numpy (>=1.26.4)
Requires-Dist: openpyxl (>=3.1)
Requires-Dist: pandas (>=2.2.2)
Requires-Dist: psycopg[binary] (>=3.2)
Requires-Dist: pydantic (>=2.10.3)
Requires-Dist: pydantic-extra-types[semver]
Requires-Dist: pydantic-settings (>=2.12.0,<3)
Requires-Dist: python-dateutil (>=2.9,<3)
Requires-Dist: pytz (>=2024.1)
Requires-Dist: pyyaml (>=6)
Requires-Dist: roman (>=4.2)
Requires-Dist: shapely (>=2.0.4)
Requires-Dist: sqlalchemy (>=2.0.36)
Requires-Dist: typer (>=0.15.0)
Project-URL: Homepage, https://gitlab.opencode.de/xleitstelle/xplanung/xplan-tools
Project-URL: Issues, https://gitlab.opencode.de/xleitstelle/xplanung/xplan-tools/-/issues
